<?xml version="1.0" encoding="UTF-8"?>
<record_update table="sc_cat_item_category">
    <sc_cat_item_category action="INSERT_OR_UPDATE">
        <sc_cat_item display_value="NBS Ticket">9ab4c871db151300fa7859d0cf9619b1</sc_cat_item>
        <sc_category display_value="Can We Help You?">e15706fc0a0a0aa7007fc21e1ab70c2f</sc_category>
        <sys_class_name>sc_cat_item_category</sys_class_name>
        <sys_created_by>admin</sys_created_by>
        <sys_created_on>2018-04-06 13:34:30</sys_created_on>
        <sys_id>58b254b9db151300fa7859d0cf96190f</sys_id>
        <sys_mod_count>0</sys_mod_count>
        <sys_name>Can We Help You?.NBS Ticket</sys_name>
        <sys_package display_value="NBS" source="x_184121_nbs">3e3a8134dbd11300fa7859d0cf9619d1</sys_package>
        <sys_policy/>
        <sys_scope display_value="NBS">3e3a8134dbd11300fa7859d0cf9619d1</sys_scope>
        <sys_update_name>sc_cat_item_category_58b254b9db151300fa7859d0cf96190f</sys_update_name>
        <sys_updated_by>admin</sys_updated_by>
        <sys_updated_on>2018-04-06 13:34:30</sys_updated_on>
    </sc_cat_item_category>
</record_update>
